a_pandas_ex_group_coordinates_by_distance/LICENSE
a_pandas_ex_group_coordinates_by_distance/README.MD
a_pandas_ex_group_coordinates_by_distance/__init__.py
a_pandas_ex_group_coordinates_by_distance/requirements.txt
a_pandas_ex_group_coordinates_by_distance/thirdparty.json
a_pandas_ex_group_coordinates_by_distance-0.10.dist-info/LICENSE.rst
a_pandas_ex_group_coordinates_by_distance-0.10.dist-info/METADATA
a_pandas_ex_group_coordinates_by_distance-0.10.dist-info/WHEEL
a_pandas_ex_group_coordinates_by_distance-0.10.dist-info/top_level.txt
a_pandas_ex_group_coordinates_by_distance-0.10.dist-info/RECORD
