Metadata-Version: 2.1
Name: a-pandas-ex-group-coordinates-by-distance
Version: 0.10
Summary: Group coordinates by euclidean distance
Home-page: https://github.com/hansalemaos/a_pandas_ex_group_coordinates_by_distance
Author: Johannes Fischer
Author-email: <aulasparticularesdealemaosp@gmail.com>
License: MIT
Keywords: opencv,cv2,coordinates,pandas
Classifier: Development Status :: 4 - Beta
Classifier: Programming Language :: Python :: 3 :: Only
Classifier: Programming Language :: Python :: 3.9
Classifier: Topic :: Scientific/Engineering :: Visualization
Classifier: Topic :: Software Development :: Libraries :: Python Modules
Classifier: Topic :: Text Editors :: Text Processing
Classifier: Topic :: Text Processing :: General
Classifier: Topic :: Text Processing :: Indexing
Classifier: Topic :: Text Processing :: Filters
Classifier: Topic :: Utilities
License-File: LICENSE.rst
Requires-Dist: numpy
Requires-Dist: pandas
